{
    "nodes" : [
        {
            "id": 0,
            "label": ":COMPONENT",
            "attributes": {
                "is_node": true,
                "translations": {"fr": ["nom0_a"], "en": ["name0_a", "name0_b"]},
                "file": {"path": "/...", "line": 0}
            }
        },
        {
            "id": 1,
            "label": ":NODE:COMPONENT",
            "attributes": {
                "is_node": false,
                "translations": {"fr": ["nom1_a"], "en": ["name1_a"]},
                "file": {"path": "/...", "line": 0}
            }
        },
        {
            "id": 2,
            "label": "LINK",
            "attributes": {
                "translations": {"fr": ["nom1_a"], "en": ["name1_a"]},
                "file": {"path": "/...", "line": 0}
            }
        }
    ],
    "edges": [ 
        {
            "src": 0,
            "tgt": 1,
            "label": "COMPOSED_BY",
            "attributes": {
                "path": "/ROOT/0"
            }
        }
        //,
        // {
        //     "src": 0,
        //     "tgt": 1,
        //     "label": "RELATION",
        //     "attributes": {
        //         "link": {"id": 3}
        //     }
        // }
    ]
}